tfm/__init__.py
tfm/__main__.py
tfm/bookmarks_model.py
tfm/extract_worker.py
tfm/form.py
tfm/mounts_model.py
tfm/paste_worker.py
tfm/stack.py
tfm/tfm.py
tfm/utility.py
tfm-0.3.3a0.dist-info/LICENSE
tfm-0.3.3a0.dist-info/METADATA
tfm-0.3.3a0.dist-info/WHEEL
tfm-0.3.3a0.dist-info/top_level.txt
tfm-0.3.3a0.dist-info/RECORD
