Metadata-Version: 2.1
Name: tfm
Version: 0.3.3a0
Summary: A simple and Qt file manager for Linux
Home-page: https://github.com/tmahlburg/tfm
Author: Till Mahlburg
License: GPLv3
Classifier: Development Status :: 3 - Alpha
Classifier: Environment :: X11 Applications :: Qt
Classifier: Programming Language :: Python :: 3
Classifier: License :: OSI Approved :: GNU General Public License v3 (GPLv3)
Classifier: Natural Language :: English
Classifier: Operating System :: POSIX :: Linux
Classifier: Intended Audience :: End Users/Desktop
Classifier: Topic :: Desktop Environment :: File Managers
Requires-Python: >=3.7
License-File: LICENSE
Requires-Dist: pyside6
Requires-Dist: prefixed
Requires-Dist: send2trash
Requires-Dist: pyudev
